tgp/__init__.py
tgp/example.py
tgp-0.0.1.dist-info/LICENSE
tgp-0.0.1.dist-info/METADATA
tgp-0.0.1.dist-info/WHEEL
tgp-0.0.1.dist-info/top_level.txt
tgp-0.0.1.dist-info/RECORD
