Metadata-Version: 2.1
Name: tgp
Version: 0.0.1
Summary: A platform for building terminal games
Home-page: https://github.com/cli-games/launcher
Author: Kieran Wood
Author-email: kieran@canadiancoding.ca
License: UNKNOWN
Platform: UNKNOWN
Classifier: Programming Language :: Python :: 3
Classifier: Operating System :: OS Independent
Classifier: Development Status :: 1 - Planning
Requires-Dist: docopt
Provides-Extra: dev
Requires-Dist: nox ; extra == 'dev'
Requires-Dist: pytest ; extra == 'dev'
Requires-Dist: mkdocs ; extra == 'dev'
Requires-Dist: mkdocs-bootstrap386 ; extra == 'dev'
